xcube_4d_viewer/__init__.py
xcube_4d_viewer/api.py
xcube_4d_viewer/context.py
xcube_4d_viewer/controllers.py
xcube_4d_viewer/plugin.py
xcube_4d_viewer/route_parameters.py
xcube_4d_viewer/routes.py
xcube_4d_viewer/tile.py
xcube_4d_viewer/helpers/__init__.py
xcube_4d_viewer/helpers/general_helpers.py
xcube_4d_viewer/helpers/image_functions.py
xcube_4d_viewer/helpers/serialising.py
xcube_4d_viewer-1.0.16.dist-info/LICENSE
xcube_4d_viewer-1.0.16.dist-info/METADATA
xcube_4d_viewer-1.0.16.dist-info/WHEEL
xcube_4d_viewer-1.0.16.dist-info/entry_points.txt
xcube_4d_viewer-1.0.16.dist-info/top_level.txt
xcube_4d_viewer-1.0.16.dist-info/RECORD
