Metadata-Version: 2.1
Name: xcube_4d_viewer
Version: 1.0.16
Summary: API extension to the xcube server allowing cubes to be viewed in the Earthwave 4D viewer.
Author: Earthwave Ltd
Author-email: info@earthwave.co.uk
License: MIT
Requires-Python: >=3.9
License-File: LICENSE
